migmanager/__init__.py
migmanager/monitor.py
migmanager/run_jobs.py
migmanager/scheduler.py
migmanager/utils.py
migmanager-0.1.0.dist-info/LICENSE
migmanager-0.1.0.dist-info/METADATA
migmanager-0.1.0.dist-info/WHEEL
migmanager-0.1.0.dist-info/entry_points.txt
migmanager-0.1.0.dist-info/top_level.txt
migmanager-0.1.0.dist-info/RECORD
