Metadata-Version: 2.2
Name: migmanager
Version: 0.1.0
Summary: A Python package for managing and scheduling jobs on MIG-enabled GPUs dynamically.
Home-page: https://github.com/JiteshRajpal/migmanager.git
Author: Jitesh Rajpal
Author-email: jiteshrajpal2508@gmail.com
Classifier: Programming Language :: Python :: 3
Classifier: License :: OSI Approved :: MIT License
Classifier: Operating System :: OS Independent
Requires-Python: >=3.7
License-File: LICENSE
Requires-Dist: setuptools
Dynamic: author
Dynamic: author-email
Dynamic: classifier
Dynamic: description
Dynamic: description-content-type
Dynamic: home-page
Dynamic: requires-dist
Dynamic: requires-python
Dynamic: summary
